{
"#DoItForTheDream": {
"Atlanta Hawks": 1
},
"#hawkyeah": {
"Atlanta Hawks": 1
},
"#ForTheA": {
"Atlanta Hawks": 2
},
"#JudgesGonnaJudge": {
"Atlanta Hawks": 1
},
"#UFC": {
"Atlanta Hawks": 1
},
"#MMA": {
"Atlanta Hawks": 1
},
"#WarriorsGround": {
"Atlanta Hawks": 1,
"Charlotte Hornets": 1,
"Dallas Mavericks": 1,
"Denver Nuggets": 1,
"Houston Rockets": 1,
"Utah Jazz": 1
},
"#MedTwitter": {
"Atlanta Hawks": 1,
"Los Angeles Clippers": 1
},
"#SurgeryTwitter": {
"Atlanta Hawks": 1,
"Los Angeles Clippers": 1
},
"#NBA75": {
"Atlanta Hawks": 1,
"Los Angeles Clippers": 1,
"Washington Wizards": 1
},
"#SnackFlashback75": {
"Atlanta Hawks": 1,
"Los Angeles Clippers": 1
},
"#ASBrS2022": {
"Atlanta Hawks": 1,
"Los Angeles Clippers": 1
},
"#camisasdetimes": {
"Atlanta Hawks": 3,
"New York Knicks": 3
},
"#colecionador": {
"Atlanta Hawks": 3,
"New York Knicks": 3
},
"#classicshirts": {
"Atlanta Hawks": 3,
"New York Knicks": 3
},
"#classicfootballshirts": {
"Atlanta Hawks": 3,
"New York Knicks": 3
},
"#camisasclassicas": {
"Atlanta Hawks": 2,
"New York Knicks": 2
},
"#camisasantigas": {
"Atlanta Hawks": 3,
"New York Knicks": 3
},
"#footballshirts": {
"Atlanta Hawks": 4,
"New York Knicks": 4
},
"#oldfootballshirts": {
"Atlanta Hawks": 3,
"New York Knicks": 3
},
"#feyenoord": {
"Atlanta Hawks": 1,
"New York Knicks": 1
},
"#roterdam": {
"Atlanta Hawks": 1,
"New York Knicks": 1
},
"#thenetherlands": {
"Atlanta Hawks": 1,
"New York Knicks": 1
},
"#belem": {
"Atlanta Hawks": 1,
"New York Knicks": 1
},
"#paysandu": {
"Atlanta Hawks": 1,
"New York Knicks": 1
},
"#pap": {
"Atlanta Hawks": 1,
"New York Knicks": 1
},
"#mangueirao": {
"Atlanta Hawks": 1,
"New York Knicks": 1
},
"#defensorsporting": {
"Atlanta Hawks": 1,
"New York Knicks": 1
},
"#montevideo": {
"Atlanta Hawks": 1,
"New York Knicks": 1
},
"#eltuerto": {
"Atlanta Hawks": 1,
"New York Knicks": 1
},
"#NOQUITINNY": {
"Atlanta Hawks": 1
},
"#STLCards": {
"Atlanta Hawks": 1
},
"#NASCAR": {
"Atlanta Hawks": 1
},
"#GatorsWin": {
"Atlanta Hawks": 1
},
"#GoGators": {
"Atlanta Hawks": 1
},
"#InternationalWomensDay": {
"Atlanta Hawks": 1
},
"#TedLasso": {
"Atlanta Hawks": 1
},
"#Redemption": {
"Atlanta Hawks": 1
},
"#VoteJasonCarrieCMT": {
"Atlanta Hawks": 1
},
"#CMTAwards": {
"Atlanta Hawks": 1,
"Cleveland Cavaliers": 1,
"Detroit Pistons": 1
},
"#IStandWithAmberHeard": {
"Atlanta Hawks": 1,
"Chicago Bulls": 1,
"Houston Rockets": 1,
"New York Knicks": 1,
"Phoenix Suns": 1
},
"#DallasCowboys": {
"Atlanta Hawks": 1
},
"#stoopidpigeon": {
"Boston Celtics": 1,
"Brooklyn Nets": 1,
"Dallas Mavericks": 1,
"Indiana Pacers": 1,
"Los Angeles Clippers": 1,
"Memphis Grizzlies": 1,
"Miami Heat": 1,
"Milwaukee Bucks": 1,
"Minnesota Timberwolves": 1,
"New York Knicks": 1,
"Oklahoma City Thunder": 1,
"Phoenix Suns": 1,
"Washington Wizards": 1
},
"#NewProfilePic": {
"Boston Celtics": 2,
"Brooklyn Nets": 1,
"Charlotte Hornets": 4,
"Cleveland Cavaliers": 1,
"Dallas Mavericks": 1,
"Denver Nuggets": 1,
"Detroit Pistons": 2,
"Houston Rockets": 2,
"Indiana Pacers": 1,
"Los Angeles Clippers": 1,
"Los Angeles Lakers": 2,
"Memphis Grizzlies": 3,
"Miami Heat": 2,
"Milwaukee Bucks": 1,
"Minnesota Timberwolves": 2,
"New Orleans Pelicans": 1,
"New York Knicks": 2,
"Oklahoma City Thunder": 1,
"Orlando Magic": 2,
"Phoenix Suns": 1,
"Portland Trail Blazers": 3,
"San Antonio Spurs": 3,
"Utah Jazz": 1,
"Washington Wizards": 2
},
"#NewNFTProfilePic": {
"Boston Celtics": 1,
"Brooklyn Nets": 1,
"Dallas Mavericks": 1,
"Indiana Pacers": 1,
"Los Angeles Clippers": 1,
"Memphis Grizzlies": 1,
"Miami Heat": 1,
"Milwaukee Bucks": 1,
"Minnesota Timberwolves": 1,
"New York Knicks": 1,
"Oklahoma City Thunder": 1,
"Phoenix Suns": 1,
"Washington Wizards": 1
},
"#nftpfp": {
"Boston Celtics": 1,
"Brooklyn Nets": 1,
"Dallas Mavericks": 1,
"Indiana Pacers": 1,
"Los Angeles Clippers": 1,
"Memphis Grizzlies": 1,
"Miami Heat": 1,
"Milwaukee Bucks": 1,
"Minnesota Timberwolves": 1,
"New York Knicks": 1,
"Oklahoma City Thunder": 1,
"Phoenix Suns": 1,
"Washington Wizards": 1
},
"#pfpNFT": {
"Boston Celtics": 1,
"Brooklyn Nets": 1,
"Dallas Mavericks": 1,
"Indiana Pacers": 1,
"Los Angeles Clippers": 1,
"Memphis Grizzlies": 1,
"Miami Heat": 1,
"Milwaukee Bucks": 1,
"Minnesota Timberwolves": 1,
"New York Knicks": 1,
"Oklahoma City Thunder": 1,
"Phoenix Suns": 1,
"Washington Wizards": 1
},
"#feels": {
"Boston Celtics": 1
},
"#MoonKnight": {
"Boston Celtics": 1
},
"#GoFundMe": {
"Boston Celtics": 1,
"Brooklyn Nets": 1,
"Chicago Bulls": 1,
"Milwaukee Bucks": 1,
"Philadelphia 76ers": 1
},
"#SocialDM": {
"Boston Celtics": 2
},
"#jointhewave": {
"Boston Celtics": 2
},
"#trending": {
"Boston Celtics": 2
},
"#cancelAdamSchefter": {
"Boston Celtics": 1
},
"#Greeks4Trump": {
"Boston Celtics": 1
},
"#MAGA": {
"Boston Celtics": 1
},
"#TheBachelor": {
"Boston Celtics": 1
},
"#noshameinmygame": {
"Boston Celtics": 1
},
"#byewill": {
"Boston Celtics": 1
},
"#RIPProof": {
"Boston Celtics": 1
},
"#RIPPROOF": {
"Boston Celtics": 1
},
"#TilesHop": {
"Boston Celtics": 1,
"Charlotte Hornets": 1,
"Detroit Pistons": 1,
"Los Angeles Clippers": 1,
"New Orleans Pelicans": 1,
"New York Knicks": 1
},
"#MusicGame": {
"Boston Celtics": 1,
"Charlotte Hornets": 1,
"Detroit Pistons": 1,
"Los Angeles Clippers": 1,
"New Orleans Pelicans": 1,
"New York Knicks": 1
},
"#Playing": {
"Boston Celtics": 1,
"Charlotte Hornets": 1,
"Detroit Pistons": 1,
"Los Angeles Clippers": 1,
"New Orleans Pelicans": 1,
"New York Knicks": 1
},
"#Mobile": {
"Boston Celtics": 1,
"Charlotte Hornets": 1,
"Detroit Pistons": 1,
"Los Angeles Clippers": 1,
"New Orleans Pelicans": 1,
"New York Knicks": 1
},
"#Game": {
"Boston Celtics": 1,
"Charlotte Hornets": 1,
"Detroit Pistons": 1,
"Los Angeles Clippers": 1,
"New Orleans Pelicans": 1,
"New York Knicks": 1
},
"#Fun": {
"Boston Celtics": 1,
"Charlotte Hornets": 1,
"Detroit Pistons": 1,
"Los Angeles Clippers": 1,
"New Orleans Pelicans": 1,
"New York Knicks": 1
},
"#Trending": {
"Boston Celtics": 1,
"Charlotte Hornets": 1,
"Detroit Pistons": 1,
"Los Angeles Clippers": 1,
"New Orleans Pelicans": 1,
"New York Knicks": 1
},
"#Amanotes": {
"Boston Celtics": 1,
"Charlotte Hornets": 1,
"Detroit Pistons": 1,
"Los Angeles Clippers": 1,
"New Orleans Pelicans": 1,
"New York Knicks": 1
},
"#UFC273": {
"Brooklyn Nets": 1
},
"#TheShop": {
"Charlotte Hornets": 1
},
"#TheBrotherhood": {
"Charlotte Hornets": 1
},
"#AllFly": {
"Charlotte Hornets": 1
},
"#nftart": {
"Charlotte Hornets": 1,
"San Antonio Spurs": 2,
"Utah Jazz": 2
},
"#nft": {
"Charlotte Hornets": 1,
"San Antonio Spurs": 2,
"Utah Jazz": 2
},
"#TakeN": {
"Charlotte Hornets": 1
},
"#TakeNote": {
"Charlotte Hornets": 1
},
"#sportsphotography": {
"Chicago Bulls": 1
},
"#flagfootball": {
"Chicago Bulls": 1
},
"#askingwhy": {
"Chicago Bulls": 1
},
"#rhsummit": {
"Chicago Bulls": 2
},
"#heeleffect": {
"Chicago Bulls": 1,
"Denver Nuggets": 1
},
"#AllForFans": {
"Cleveland Cavaliers": 1
},
"#Browns": {
"Cleveland Cavaliers": 2
},
"#GamblingTwitter": {
"Cleveland Cavaliers": 1
},
"#LedZeppelin": {
"Cleveland Cavaliers": 1,
"Indiana Pacers": 1,
"Los Angeles Clippers": 1,
"New Orleans Pelicans": 1,
"New York Knicks": 1,
"Utah Jazz": 1
},
"#rocknroll": {
"Cleveland Cavaliers": 1,
"Indiana Pacers": 1,
"Los Angeles Clippers": 1,
"New Orleans Pelicans": 1,
"New York Knicks": 1,
"Phoenix Suns": 1,
"Utah Jazz": 1
},
"#Letemknow": {
"Cleveland Cavaliers": 1
},
"#LetEmKnow": {
"Cleveland Cavaliers": 1
},
"#jasonaldean": {
"Cleveland Cavaliers": 1
},
"#VoteCodyCMT": {
"Cleveland Cavaliers": 1,
"Detroit Pistons": 1,
"Oklahoma City Thunder": 1
},
"#MyTwitterAnniversary": {
"Cleveland Cavaliers": 1,
"Oklahoma City Thunder": 1
},
"#RipCity": {
"Dallas Mavericks": 2,
"Phoenix Suns": 2,
"Portland Trail Blazers": 1
},
"#UnfinishedBusiness": {
"Dallas Mavericks": 1
},
"#UFODeclassifiedLIVE": {
"Dallas Mavericks": 1
},
"#DwightPowell": {
"Dallas Mavericks": 1
},
"#NBACommunityAssistAward": {
"Dallas Mavericks": 1
},
"#KwakuTheTravel": {
"Dallas Mavericks": 1
},
"#SRM3224": {
"Denver Nuggets": 1
},
"#nerd": {
"Denver Nuggets": 1
},
"#downbad": {
"Denver Nuggets": 1
},
"#CommitToThePAW": {
"Denver Nuggets": 1
},
"#HipHop": {
"Denver Nuggets": 3
},
"#Spotify": {
"Denver Nuggets": 3
},
"#Apple": {
"Denver Nuggets": 3
},
"#Youtube": {
"Denver Nuggets": 3
},
"#LeBronJames": {
"Denver Nuggets": 1
},
"#NBAAllStar": {
"Denver Nuggets": 1,
"Memphis Grizzlies": 1
},
"#DB4L": {
"Denver Nuggets": 1
},
"#Seahawks": {
"Denver Nuggets": 1
},
"#BEAUTIFUL": {
"Detroit Pistons": 1
},
"#wedding": {
"Detroit Pistons": 1
},
"#musicians": {
"Detroit Pistons": 1
},
"#musicianslife": {
"Detroit Pistons": 1
},
"#weddingband": {
"Detroit Pistons": 1
},
"#eventplanner": {
"Detroit Pistons": 1
},
"#willistead": {
"Detroit Pistons": 1
},
"#windsormusic": {
"Detroit Pistons": 1
},
"#music": {
"Detroit Pistons": 1,
"Phoenix Suns": 1,
"Utah Jazz": 1
},
"#livemusic": {
"Detroit Pistons": 1,
"Phoenix Suns": 1
},
"#band": {
"Detroit Pistons": 1
},
"#MusicMonday": {
"Detroit Pistons": 1
},
"#Ci": {
"Detroit Pistons": 1
},
"#CFPVote": {
"Detroit Pistons": 1
},
"#downtowndetroit": {
"Detroit Pistons": 1
},
"#rencen": {
"Detroit Pistons": 1
},
"#fujifilm": {
"Detroit Pistons": 1
},
"#rawdetroit": {
"Detroit Pistons": 1
},
"#urbanphotographer": {
"Detroit Pistons": 1
},
"#streetphotography": {
"Detroit Pistons": 1
},
"#OnePride": {
"Detroit Pistons": 1
},
"#Lions": {
"Detroit Pistons": 1
},
"#DetroitLions": {
"Detroit Pistons": 1
},
"#Madden22": {
"Detroit Pistons": 1
},
"#NFL": {
"Detroit Pistons": 1
},
"#DetroitRoots": {
"Detroit Pistons": 1
},
"#DefendTheDen": {
"Detroit Pistons": 1
},
"#photo": {
"Detroit Pistons": 5
},
"#ad": {
"Detroit Pistons": 1,
"New Orleans Pelicans": 1,
"Washington Wizards": 1
},
"#CaptainCragen": {
"Golden State Warriors": 1,
"Los Angeles Lakers": 1,
"Portland Trail Blazers": 1
},
"#SVU": {
"Golden State Warriors": 1,
"Los Angeles Lakers": 1,
"Portland Trail Blazers": 1
},
"#LawAndOrderSVU": {
"Golden State Warriors": 1,
"Los Angeles Lakers": 1,
"Portland Trail Blazers": 1
},
"#LawAndOrder": {
"Golden State Warriors": 1,
"Los Angeles Lakers": 1,
"Portland Trail Blazers": 1
},
"#teenporn": {
"Golden State Warriors": 1
},
"#pornpalace": {
"Golden State Warriors": 1
},
"#mysecretsound": {
"Golden State Warriors": 2
},
"#joebudden": {
"Golden State Warriors": 1
},
"#fortnite": {
"Golden State Warriors": 1
},
"#TheGreatGatsby": {
"Houston Rockets": 1
},
"#Cannes": {
"Houston Rockets": 1
},
"#LACvsLV": {
"Houston Rockets": 1
},
"#Ethiopia": {
"Houston Rockets": 1
},
"#Sudan": {
"Houston Rockets": 1
},
"#Rockets": {
"Houston Rockets": 1,
"Philadelphia 76ers": 1,
"Portland Trail Blazers": 1,
"Utah Jazz": 1
},
"#Wizards": {
"Houston Rockets": 2
},
"#DCAboveAll": {
"Houston Rockets": 2
},
"#NBAPlayoffs": {
"Houston Rockets": 2,
"Miami Heat": 1,
"Minnesota Timberwolves": 1
},
"#NBA": {
"Houston Rockets": 2,
"Memphis Grizzlies": 1,
"Orlando Magic": 1,
"San Antonio Spurs": 1,
"Washington Wizards": 1
},
"#basketball": {
"Houston Rockets": 2,
"Philadelphia 76ers": 3,
"Portland Trail Blazers": 3,
"Utah Jazz": 3
},
"#Viral": {
"Houston Rockets": 2
},
"#Hornets": {
"Houston Rockets": 2
},
"#BidenBorderCrisis": {
"Houston Rockets": 1
},
"#SpaceCity": {
"Houston Rockets": 1
},
"#FeverDraft": {
"Indiana Pacers": 2,
"Los Angeles Clippers": 1,
"Los Angeles Lakers": 1,
"Memphis Grizzlies": 1,
"Miami Heat": 1,
"Milwaukee Bucks": 1,
"Minnesota Timberwolves": 1,
"New Orleans Pelicans": 1,
"New York Knicks": 1,
"Oklahoma City Thunder": 1,
"Orlando Magic": 1,
"Philadelphia 76ers": 1,
"Phoenix Suns": 1,
"Portland Trail Blazers": 1,
"San Antonio Spurs": 1,
"Toronto Raptors": 1,
"Utah Jazz": 1,
"Washington Wizards": 1
},
"#pacersgamenight": {
"Indiana Pacers": 1
},
"#FrozenFour": {
"Indiana Pacers": 1
},
"#PioneerTogether": {
"Indiana Pacers": 1
},
"#GoCards": {
"Indiana Pacers": 1
},
"#MarchMadness": {
"Indiana Pacers": 1
},
"#NewsBreak": {
"Indiana Pacers": 1
},
"#TakeCover": {
"Indiana Pacers": 1
},
"#WWERaw": {
"Indiana Pacers": 1
},
"#Fever4Life": {
"Indiana Pacers": 1
},
"#GoStanford": {
"Indiana Pacers": 1
},
"#LovetheGame": {
"Indiana Pacers": 1
},
"#Shoot360": {
"Indiana Pacers": 2
},
"#Always100": {
"Indiana Pacers": 1
},
"#IndyBasketball": {
"Indiana Pacers": 1
},
"#StrangerThings4": {
"Los Angeles Clippers": 1
},
"#giveaway": {
"Los Angeles Clippers": 1,
"Phoenix Suns": 1
},
"#ClipperNation": {
"Los Angeles Clippers": 1
},
"#WIT": {
"Los Angeles Clippers": 1
},
"#GoTops": {
"Los Angeles Clippers": 1
},
"#ArmyDay": {
"Los Angeles Lakers": 1,
"Milwaukee Bucks": 1
},
"#BlackClover": {
"Los Angeles Lakers": 1
},
"#anime": {
"Los Angeles Lakers": 1
},
"#Memes": {
"Los Angeles Lakers": 2
},
"#offensivememes": {
"Los Angeles Lakers": 1
},
"#Spiderman": {
"Los Angeles Lakers": 1
},
"#TipWithBrave": {
"Los Angeles Lakers": 2,
"Memphis Grizzlies": 2,
"Milwaukee Bucks": 2,
"Minnesota Timberwolves": 2,
"Philadelphia 76ers": 2,
"Phoenix Suns": 2,
"San Antonio Spurs": 2
},
"#KC": {
"Los Angeles Lakers": 1
},
"#TS": {
"Los Angeles Lakers": 1
},
"#Amakhosi4Life": {
"Los Angeles Lakers": 1
},
"#DStvPrem": {
"Los Angeles Lakers": 1
},
"#GrzNxtGen": {
"Memphis Grizzlies": 1
},
"#MEMPHIS": {
"Memphis Grizzlies": 1
},
"#Grizzlies": {
"Memphis Grizzlies": 1
},
"#LightUpMemphis": {
"Memphis Grizzlies": 1
},
"#MemThis": {
"Memphis Grizzlies": 1
},
"#ThunderUp": {
"Memphis Grizzlies": 1
},
"#TrustTheProcess": {
"Memphis Grizzlies": 1
},
"#NFLHonors": {
"Memphis Grizzlies": 1
},
"#JaMorant": {
"Memphis Grizzlies": 1
},
"#NBAAIIStar": {
"Memphis Grizzlies": 1
},
"#supernecessary": {
"Memphis Grizzlies": 1
},
"#Wu": {
"Memphis Grizzlies": 1
},
"#concubine": {
"Memphis Grizzlies": 1
},
"#Empress": {
"Memphis Grizzlies": 1
},
"#Suns": {
"Memphis Grizzlies": 1
},
"#Islanders": {
"Memphis Grizzlies": 1
},
"#sheep": {
"Memphis Grizzlies": 1
},
"#Hiroshima": {
"Memphis Grizzlies": 1
},
"#gas": {
"Memphis Grizzlies": 1
},
"#ww2": {
"Memphis Grizzlies": 1
},
"#Japan": {
"Memphis Grizzlies": 1
},
"#STAYME7O": {
"Miami Heat": 1
},
"#TheUltimatum": {
"Miami Heat": 1
},
"#ElectionDay": {
"Miami Heat": 1
},
"#GDPR": {
"Miami Heat": 1
},
"#CCPA": {
"Miami Heat": 1
},
"#wankchat": {
"Miami Heat": 1
},
"#wankbattle": {
"Miami Heat": 1
},
"#goon": {
"Miami Heat": 1
},
"#cum": {
"Miami Heat": 1
},
"#no": {
"Miami Heat": 1
},
"#MetaQuestPlayIn": {
"Miami Heat": 1,
"Minnesota Timberwolves": 1
},
"#obbpd": {
"Miami Heat": 1
},
"#coffeefac": {
"Miami Heat": 1
},
"#angrybarista": {
"Miami Heat": 1
},
"#CoffeeLover": {
"Miami Heat": 1
},
"#TrustTheClimb": {
"Milwaukee Bucks": 1
},
"#WVUFootball": {
"Milwaukee Bucks": 1
},
"#WVU": {
"Milwaukee Bucks": 1
},
"#Nanton": {
"Milwaukee Bucks": 1
},
"#history": {
"Milwaukee Bucks": 1
},
"#alberta": {
"Milwaukee Bucks": 1
},
"#yyc": {
"Milwaukee Bucks": 2
},
"#yyccc": {
"Milwaukee Bucks": 2
},
"#sanctions": {
"Milwaukee Bucks": 1
},
"#Russia": {
"Milwaukee Bucks": 1
},
"#Ukraine": {
"Milwaukee Bucks": 1,
"Oklahoma City Thunder": 1
},
"#Putin": {
"Milwaukee Bucks": 1
},
"#Rhamphyre": {
"Milwaukee Bucks": 1
},
"#AZ": {
"Milwaukee Bucks": 1
},
"#NY": {
"Milwaukee Bucks": 1
},
"#abbott": {
"Milwaukee Bucks": 1
},
"#FBI": {
"Milwaukee Bucks": 1
},
"#DOJ": {
"Milwaukee Bucks": 1
},
"#OIG": {
"Milwaukee Bucks": 1
},
"#OSC": {
"Milwaukee Bucks": 1
},
"#ukraine": {
"Milwaukee Bucks": 1
},
"#Newcastle": {
"Milwaukee Bucks": 1
},
"#Tottenham": {
"Milwaukee Bucks": 1
},
"#Bitcoin": {
"Minnesota Timberwolves": 2,
"Orlando Magic": 2,
"San Antonio Spurs": 1,
"Utah Jazz": 1
},
"#jonnysbeer": {
"Minnesota Timberwolves": 1
},
"#thecircuit": {
"New Orleans Pelicans": 1
},
"#FridayFeeling": {
"New Orleans Pelicans": 1
},
"#LedoPizza": {
"New Orleans Pelicans": 1
},
"#southernbugs": {
"New Orleans Pelicans": 1
},
"#crawdaddys": {
"New Orleans Pelicans": 1
},
"#GetInMyBelly": {
"New Orleans Pelicans": 1
},
"#WHODAT": {
"New Orleans Pelicans": 2
},
"#AI": {
"New York Knicks": 1
},
"#TikTok": {
"New York Knicks": 1
},
"#Privacy": {
"New York Knicks": 1
},
"#COVID": {
"New York Knicks": 1
},
"#China": {
"New York Knicks": 1
},
"#semiconductor": {
"New York Knicks": 1
},
"#OpeningDay": {
"New York Knicks": 1
},
"#Yankees": {
"New York Knicks": 4
},
"#MLB": {
"New York Knicks": 4
},
"#yankeestadium": {
"New York Knicks": 1
},
"#NewYork": {
"New York Knicks": 1
},
"#Livestream": {
"New York Knicks": 1
},
"#YouTube": {
"New York Knicks": 1
},
"#PodcastAndChill": {
"New York Knicks": 1
},
"#espn": {
"New York Knicks": 1
},
"#SundayNightBaseball": {
"New York Knicks": 1
},
"#baseball": {
"New York Knicks": 1
},
"#GiveawayNFT": {
"New York Knicks": 1
},
"#kahiru": {
"New York Knicks": 1
},
"#Whitelist": {
"New York Knicks": 1,
"San Antonio Spurs": 2,
"Utah Jazz": 2
},
"#NFTGiveaways": {
"New York Knicks": 1
},
"#Wizardpass": {
"New York Knicks": 1
},
"#BestBarChamps": {
"Oklahoma City Thunder": 1
},
"#SouljaStars": {
"Oklahoma City Thunder": 1
},
"#souljastars": {
"Oklahoma City Thunder": 1
},
"#OnTheRunTo200K": {
"Oklahoma City Thunder": 1
},
"#OUDNA": {
"Oklahoma City Thunder": 1
},
"#GoBulldog": {
"Oklahoma City Thunder": 1
},
"#ProBowlVote": {
"Orlando Magic": 1
},
"#NFTdrop": {
"Orlando Magic": 1
},
"#crypto": {
"Orlando Magic": 1,
"San Antonio Spurs": 1,
"Utah Jazz": 1
},
"#BSC": {
"Orlando Magic": 1,
"San Antonio Spurs": 1,
"Utah Jazz": 1
},
"#passiveincome": {
"Orlando Magic": 1,
"San Antonio Spurs": 1,
"Utah Jazz": 1
},
"#RestoreTheSnyderVerse": {
"Orlando Magic": 2
},
"#IStandWithRayFisher": {
"Orlando Magic": 1
},
"#Restore": {
"Orlando Magic": 1
},
"#RepBX": {
"Orlando Magic": 1
},
"#F1": {
"Orlando Magic": 1
},
"#Melbourne": {
"Orlando Magic": 1
},
"#Jokic": {
"Orlando Magic": 1
},
"#GuoAilun": {
"Orlando Magic": 1
},
"#MCFC": {
"Orlando Magic": 1
},
"#LFC": {
"Orlando Magic": 1
},
"#Gard": {
"Orlando Magic": 1
},
"#Dodgers": {
"Orlando Magic": 1
},
"#WorldSeries": {
"Orlando Magic": 1
},
"#nba": {
"Philadelphia 76ers": 1,
"Portland Trail Blazers": 1,
"Utah Jazz": 1
},
"#curry": {
"Philadelphia 76ers": 1,
"Portland Trail Blazers": 1,
"Utah Jazz": 1
},
"#lamelo": {
"Philadelphia 76ers": 2,
"Portland Trail Blazers": 2,
"Utah Jazz": 2
},
"#chinohills": {
"Philadelphia 76ers": 1,
"Portland Trail Blazers": 1,
"Utah Jazz": 1
},
"#HereTheyCome": {
"Philadelphia 76ers": 1
},
"#phillies": {
"Philadelphia 76ers": 1
},
"#citizensbankpark": {
"Philadelphia 76ers": 1
},
"#RingTheBell": {
"Philadelphia 76ers": 3
},
"#CNNNYE": {
"Philadelphia 76ers": 1
},
"#CHSleepOut": {
"Philadelphia 76ers": 1
},
"#AccentureMoments": {
"Philadelphia 76ers": 1
},
"#XR": {
"Philadelphia 76ers": 1
},
"#ImmersiveLea": {
"Philadelphia 76ers": 1
},
"#UltimatumNetflix": {
"Philadelphia 76ers": 1
},
"#sellfeetpics": {
"Philadelphia 76ers": 1
},
"#buyfeetpics": {
"Philadelphia 76ers": 1
},
"#sexyfeet": {
"Philadelphia 76ers": 1
},
"#feetpics": {
"Philadelphia 76ers": 1
},
"#hotfeet": {
"Philadelphia 76ers": 1
},
"#prettyfeet": {
"Philadelphia 76ers": 1
},
"#SunDevils": {
"Phoenix Suns": 1
},
"#prizes": {
"Phoenix Suns": 1
},
"#RockFest2017": {
"Phoenix Suns": 1
},
"#NationalDayofHope": {
"Phoenix Suns": 1
},
"#RaisedUpRightTour": {
"Phoenix Suns": 1
},
"#CavsClippers": {
"Phoenix Suns": 2
},
"#vbareveal": {
"Phoenix Suns": 1
},
"#P2E": {
"Phoenix Suns": 1
},
"#PlaytoEarn": {
"Phoenix Suns": 1
},
"#WAXP": {
"Phoenix Suns": 1
},
"#Blockchain": {
"Phoenix Suns": 1
},
"#NFTGames": {
"Phoenix Suns": 1
},
"#NFTGiveaway": {
"Phoenix Suns": 1,
"San Antonio Spurs": 2,
"Utah Jazz": 2
},
"#KomiSan": {
"Portland Trail Blazers": 1
},
"#SPY_FAMILY": {
"Portland Trail Blazers": 1
},
"#SPYxFamily": {
"Portland Trail Blazers": 1
},
"#fresh": {
"Portland Trail Blazers": 1
},
"#postmabonepdx": {
"Portland Trail Blazers": 2
},
"#pdxSPRING": {
"Portland Trail Blazers": 1
},
"#kgwthegoodstuff": {
"Portland Trail Blazers": 1
},
"#postmabone": {
"Portland Trail Blazers": 1
},
"#easter2022": {
"Portland Trail Blazers": 1
},
"#bunnyfoofoo": {
"Portland Trail Blazers": 1
},
"#GoodTimes": {
"Portland Trail Blazers": 1
},
"#RIPTysonKennethJohnson": {
"Portland Trail Blazers": 1
},
"#LoveMyDucks": {
"Portland Trail Blazers": 1
},
"#GoDucks": {
"Portland Trail Blazers": 1
},
"#BetterCallSaul": {
"Portland Trail Blazers": 1
},
"#HODL": {
"Portland Trail Blazers": 1
},
"#wikicatcoin": {
"Portland Trail Blazers": 1
},
"#wikicatisours": {
"Portland Trail Blazers": 1
},
"#WIKICAT": {
"Portland Trail Blazers": 1
},
"#Cryp": {
"Portland Trail Blazers": 1
},
"#rt": {
"Sacramento Kings": 2
},
"#PAKVSAUS": {
"Sacramento Kings": 1
},
"#T20WorldCup": {
"Sacramento Kings": 1
},
"#coronavirus": {
"Sacramento Kings": 1
},
"#Tablighi": {
"Sacramento Kings": 1
},
"#Jamaat": {
"Sacramento Kings": 1
},
"#ITER": {
"Sacramento Kings": 1
},
"#ITERAssemblyStarts": {
"Sacramento Kings": 1
},
"#WeAreITER": {
"Sacramento Kings": 1
},
"#NationalCheeseDay": {
"Sacramento Kings": 1
},
"#TeachersHaveFamiliesToo": {
"Sacramento Kings": 1
},
"#PaySchoolFee": {
"Sacramento Kings": 1
},
"#EducationMinisterGoesLive": {
"Sacramento Kings": 1
},
"#MobilesOnFlipkart": {
"Sacramento Kings": 1
},
"#MIDNIGHTFOOTBALLPARTY": {
"Sacramento Kings": 1
},
"#airtelnothanks": {
"Sacramento Kings": 1
},
"#airteldoesntcare": {
"Sacramento Kings": 1
},
"#INDvOMA": {
"Sacramento Kings": 1
},
"#RealJuve": {
"Sacramento Kings": 1
},
"#ipl": {
"Sacramento Kings": 1
},
"#IPL": {
"Sacramento Kings": 1
},
"#NBATwitter": {
"San Antonio Spurs": 2
},
"#nbanews": {
"San Antonio Spurs": 1
},
"#breakingnba": {
"San Antonio Spurs": 1
},
"#nfts": {
"San Antonio Spurs": 2,
"Utah Jazz": 2
},
"#NFTCommunity": {
"San Antonio Spurs": 2,
"Utah Jazz": 2
},
"#NFTartist": {
"San Antonio Spurs": 2,
"Utah Jazz": 2
},
"#NFTartists": {
"San Antonio Spurs": 2,
"Utah Jazz": 2
},
"#NFTdrops": {
"San Antonio Spurs": 4,
"Utah Jazz": 4
},
"#nftcollectors": {
"San Antonio Spurs": 2,
"Utah Jazz": 2
},
"#FreeNFT": {
"San Antonio Spurs": 2,
"Utah Jazz": 2
},
"#cryptoart": {
"San Antonio Spurs": 2,
"Utah Jazz": 2
},
"#opensea": {
"San Antonio Spurs": 2,
"Utah Jazz": 2
},
"#OpenSeaNFT": {
"San Antonio Spurs": 2,
"Utah Jazz": 2
},
"#NFTcollectibles": {
"San Antonio Spurs": 2,
"Utah Jazz": 2
},
"#cryptocurrencies": {
"San Antonio Spurs": 2,
"Utah Jazz": 2
},
"#cryptonft": {
"San Antonio Spurs": 2,
"Utah Jazz": 2
},
"#BNBChain": {
"San Antonio Spurs": 1,
"Utah Jazz": 1
},
"#CoinMarketCap": {
"San Antonio Spurs": 1,
"Utah Jazz": 1
},
"#Staking": {
"San Antonio Spurs": 1,
"Utah Jazz": 1
},
"#FBvsGS": {
"San Antonio Spurs": 1,
"Utah Jazz": 1
},
"#portraitphotographer": {
"San Antonio Spurs": 1
},
"#kinglionphotography": {
"San Antonio Spurs": 1
},
"#SmallBusiness": {
"San Antonio Spurs": 1
},
"#SCTop10": {
"San Antonio Spurs": 1
},
"#LeafsForever": {
"Toronto Raptors": 1
},
"#brokeneasel": {
"Toronto Raptors": 1
},
"#Cubs": {
"Toronto Raptors": 1
},
"#SuperRugbyPacific": {
"Toronto Raptors": 1
},
"#NRLBroncosRoosters": {
"Toronto Raptors": 1
},
"#hindi": {
"Toronto Raptors": 1
},
"#hindisong": {
"Toronto Raptors": 1
},
"#Bollywood": {
"Toronto Raptors": 1
},
"#mallu": {
"Toronto Raptors": 1
},
"#coversong": {
"Toronto Raptors": 1
},
"#canada": {
"Toronto Raptors": 1
},
"#india": {
"Toronto Raptors": 1
},
"#uk": {
"Toronto Raptors": 1
},
"#usa": {
"Toronto Raptors": 1
},
"#malayalam": {
"Toronto Raptors": 1
},
"#amateursinger": {
"Toronto Raptors": 1
},
"#vocalist": {
"Toronto Raptors": 1
},
"#rnb": {
"Toronto Raptors": 1
},
"#fyp": {
"Toronto Raptors": 1
},
"#singersongwriter": {
"Toronto Raptors": 1
},
"#nextlevel": {
"Toronto Raptors": 1
},
"#FluTruxKlan": {
"Toronto Raptors": 1
},
"#omicronvoy": {
"Toronto Raptors": 1
},
"#FortniteFlipped": {
"Toronto Raptors": 1
},
"#GoPackGo": {
"Toronto Raptors": 1
},
"#PutCheeseOnEverything": {
"Toronto Raptors": 1
},
"#blackclover": {
"Utah Jazz": 1
},
"#Animes": {
"Utah Jazz": 1
},
"#mangas": {
"Utah Jazz": 1
},
"#mangaart": {
"Utah Jazz": 1
},
"#amvs": {
"Utah Jazz": 1
},
"#AnimeArt": {
"Utah Jazz": 1
},
"#rap": {
"Utah Jazz": 1
},
"#atlanta": {
"Utah Jazz": 1
},
"#nfl": {
"Utah Jazz": 1
},
"#markofthebeast": {
"Utah Jazz": 1
},
"#illustrat": {
"Utah Jazz": 1
},
"#TokyoOlympics": {
"Utah Jazz": 1
},
"#Tokyo2020": {
"Utah Jazz": 2
},
"#SaturdayV": {
"Utah Jazz": 1
},
"#NaturePhotography": {
"Utah Jazz": 2
},
"#nature": {
"Utah Jazz": 1
},
"#flowerphotography": {
"Utah Jazz": 1
},
"#MetalGearSolid": {
"Utah Jazz": 1
},
"#GeckoLove": {
"Utah Jazz": 1
},
"#MBAtwitterContest": {
"Utah Jazz": 5
},
"#gobl": {
"Utah Jazz": 1
},
"#Family": {
"Utah Jazz": 1
},
"#NewarkStandUp": {
"Utah Jazz": 1
},
"#Bri": {
"Utah Jazz": 1
},
"#freecsgoskins": {
"Washington Wizards": 1
},
"#freeskins": {
"Washington Wizards": 1
},
"#csgogiveaways": {
"Washington Wizards": 1
},
"#csgogiveaway": {
"Washington Wizards": 1
},
"#horny": {
"Washington Wizards": 1
},
"#Truckers": {
"Washington Wizards": 2
},
"#SingleMoms": {
"Washington Wizards": 1
},
"#wetpussy": {
"Washington Wizards": 1
},
"#sex": {
"Washington Wizards": 1
},
"#sellingnudes": {
"Washington Wizards": 1
},
"#buyingnudes": {
"Washington Wizards": 1
},
"#classyAf": {
"Washington Wizards": 1
},
"#theyHateUsCuzTheyAintUs": {
"Washington Wizards": 1
},
"#confused": {
"Washington Wizards": 1
},
"#sorryMom": {
"Washington Wizards": 1
},
"#GoBlue": {
"Washington Wizards": 1
},
"#XboxSonic2Sweepstakes": {
"Washington Wizards": 1
},
"#ShareKindness": {
"Washington Wizards": 1
},
"#LakersWin": {
"Washington Wizards": 1
}
}